replace_text/__init__.py
replace_text/replace_text.py
replace_text/tests/__init__.py
replace_text/tests/test_replace_text.py
textswap-0.1.0.dist-info/METADATA
textswap-0.1.0.dist-info/WHEEL
textswap-0.1.0.dist-info/entry_points.txt
textswap-0.1.0.dist-info/licenses/LICENSE
textswap-0.1.0.dist-info/RECORD
