Metadata-Version: 2.4
Name: textswap
Version: 0.1.0
Summary: Bulk text replacement in files using dictionary mappings
Project-URL: Homepage, https://github.com/cainky/textswap
Project-URL: Repository, https://github.com/cainky/textswap
Project-URL: Issues, https://github.com/cainky/textswap/issues
Author-email: Kyle Cain <kyle@kylecain.me>
License-Expression: GPL-3.0-or-later
License-File: LICENSE
Keywords: bulk,cli,dictionary,find-replace,replace,text
Classifier: Development Status :: 4 - Beta
Classifier: Environment :: Console
Classifier: Intended Audience :: Developers
Classifier: License :: OSI Approved :: GNU General Public License v3 (GPLv3)
Classifier: Operating System :: OS Independent
Classifier: Programming Language :: Python :: 3
Classifier: Programming Language :: Python :: 3.9
Classifier: Programming Language :: Python :: 3.10
Classifier: Programming Language :: Python :: 3.11
Classifier: Programming Language :: Python :: 3.12
Classifier: Topic :: Text Processing
Classifier: Topic :: Utilities
Requires-Python: >=3.9
Requires-Dist: click>=8.0.0
Provides-Extra: dev
Requires-Dist: pytest-cov>=4.0.0; extra == 'dev'
Requires-Dist: pytest>=7.0.0; extra == 'dev'
Requires-Dist: ruff>=0.1.0; extra == 'dev'
